Workbook

Sheet 00 Cover
B2: Solar Farm Project Finance Model
B4: Project: 50 MW solar farm
B5: Purpose: asses debt capacity and equity returns
B6: Model type: project finance model
B7: Key outputs
B8: Total capex
B9: Total debt
B10: Total equity
B11: Minimum DCSR
B12: Average DCSR
B13: LLCR
B14: Equity IRR
B15: Project IRR

Sheet 01 Inputs
A2: Solar Farm Inputs
A4: Project life | B4: 25
A5: Construction years | B5: 1
A6: Capacity MW | B6: 50
A7: Capex per MW | B7: 750000
A8: Capacity factor | B8: 0.17
A9: Annual degradation | B9: 0.005
A10: PPA price per MWh | B10: 65
A11: PPA escalation | B11: 0.02
A12: Opex per MW | B12: 15000
A13: Opex escalation | B13: 0.02
A14: Debt percentage | B14: 0.65
A15: Equity percentage | B15: 0.35
... A19: LLCR discount rate | B19: 0.065
A22: All assumptions are illustrative and used for portfolio learning.

Sheet 02 Timeline
B2: Timeline
B4: Year | C4: 0 | D4: =C4 + 1 -> 1 | E4: =D4 + 1 -> 2 | F4: =E4 + 1 -> 3 | G4: =F4 + 1 -> 4 | H4: =G4 + 1 -> 5 | I4: =H4 + 1 -> 6 | J4: =I4 + 1 -> 7 | K4: =J4 + 1 -> 8 | ... AB4: =AA4 + 1 -> 25
B5: Construction flag | C5: =IF(C$4<'01 Inputs'!$B$5,1,0) -> 1 | D5: =IF(D$4<'01 Inputs'!$B$5,1,0) -> 0 | E5: =IF(E$4<'01 Inputs'!$B$5,1,0) -> 0 | F5: =IF(F$4<'01 Inputs'!$B$5,1,0) -> 0 | G5: =IF(G$4<'01 Inputs'!$B$5,1,0) -> 0 | H5: =IF(H$4<'01 Inputs'!$B$5,1,0) -> 0 | I5: =IF(I$4<'01 Inputs'!$B$5,1,0) -> 0 | J5: =IF(J$4<'01 Inputs'!$B$5,1,0) -> 0 | ... AB5: =IF(AB$4<'01 Inputs'!$B$5,1,0) -> 0
B6: Operations flag | C6: =IF(C$4>='01 Inputs'!$B$5,1,0) -> 0 | D6: =IF(D$4>='01 Inputs'!$B$5,1,0) -> 1 | E6: =IF(E$4>='01 Inputs'!$B$5,1,0) -> 1 | F6: =IF(F$4>='01 Inputs'!$B$5,1,0) -> 1 | G6: =IF(G$4>='01 Inputs'!$B$5,1,0) -> 1 | H6: =IF(H$4>='01 Inputs'!$B$5,1,0) -> 1 | I6: =IF(I$4>='01 Inputs'!$B$5,1,0) -> 1 | J6: =IF(J$4>='01 Inputs'!$B$5,1,0) -> 1 | ... AB6: =IF(AB$4>='01 Inputs'!$B$5,1,0) -> 1
B7: Debt repayment flag | C7: =IF(AND(C$4>='01 Inputs'!$B$5,C$4<='01 Inputs'!$B$17),1,0) -> 0 | D7: =IF(AND(D$4>='01 Inputs'!$B$5,D$4<='01 Inputs'!$B$17),1,0) -> 1 | E7: =IF(AND(E$4>='01 Inputs'!$B$5,E$4<='01 Inputs'!$B$17),1,0) -> 1 | F7: =IF(AND(F$4>='01 Inputs'!$B$5,F$4<='01 Inputs'!$B$17),1,0) -> 1 | G7: =IF(AND(G$4>='01 Inputs'!$B$5,G$4<='01 Inputs'!$B$17),1,0) -> 1 | H7: =IF(AND(H$4>='01 Inputs'!$B$5,H$4<='01 Inputs'!$B$17),1,0) -> 1 | I7: =IF(AND(I$4>='01 Inputs'!$B$5,I$4<='01 Inputs'!$B$17),1,0) -> 1 | J7: =IF(AND(J$4>='01 Inputs'!$B$5,J$4<='01 Inputs'!$B$17),1,0) -> 1 | ... AB7: =IF(AND(AB$4>='01 Inputs'!$B$5,AB$4<='01 Inputs'!$B$17),1,0) -> 0

Sheet 03 Construction
B2: Construction and Funding
B4: Year | C4: ='02 Timeline'!C4 -> 0 | D4: ='02 Timeline'!D4 -> 1 | E4: ='02 Timeline'!E4 -> 2 | F4: ='02 Timeline'!F4 -> 3 | G4: ='02 Timeline'!G4 -> 4 | H4: ='02 Timeline'!H4 -> 5 | I4: ='02 Timeline'!I4 -> 6 | J4: ='02 Timeline'!J4 -> 7 | ... AB4: ='02 Timeline'!AB4 -> 25
B5: Total capex | C5: ='01 Inputs'!$B$6*'01 Inputs'!$B$7 -> 37500000 | D5: ='01 Inputs'!$B$6*'01 Inputs'!$B$7 -> 37500000 | E5: ='01 Inputs'!$B$6*'01 Inputs'!$B$7 -> 37500000 | F5: ='01 Inputs'!$B$6*'01 Inputs'!$B$7 -> 37500000 | G5: ='01 Inputs'!$B$6*'01 Inputs'!$B$7 -> 37500000 | H5: ='01 Inputs'!$B$6*'01 Inputs'!$B$7 -> 37500000 | I5: ='01 Inputs'!$B$6*'01 Inputs'!$B$7 -> 37500000 | J5: ='01 Inputs'!$B$6*'01 Inputs'!$B$7 -> 37500000 | ... AB5: ='01 Inputs'!$B$6*'01 Inputs'!$B$7 -> 37500000
B6: Capex spend | C6: =C$5/'01 Inputs'!$B$5*'02 Timeline'!C5 -> 37500000 | D6: =D$5/'01 Inputs'!$B$5*'02 Timeline'!D5 -> 0 | E6: =E$5/'01 Inputs'!$B$5*'02 Timeline'!E5 -> 0 | F6: =F$5/'01 Inputs'!$B$5*'02 Timeline'!F5 -> 0 | G6: =G$5/'01 Inputs'!$B$5*'02 Timeline'!G5 -> 0 | H6: =H$5/'01 Inputs'!$B$5*'02 Timeline'!H5 -> 0 | I6: =I$5/'01 Inputs'!$B$5*'02 Timeline'!I5 -> 0 | J6: =J$5/'01 Inputs'!$B$5*'02 Timeline'!J5 -> 0 | ... AB6: =AB$5/'01 Inputs'!$B$5*'02 Timeline'!AB5 -> 0
B7: Debt drawdown | C7: =C6*'01 Inputs'!$B$14 -> 24375000 | D7: =D6*'01 Inputs'!$B$14 -> 0 | E7: =E6*'01 Inputs'!$B$14 -> 0 | F7: =F6*'01 Inputs'!$B$14 -> 0 | G7: =G6*'01 Inputs'!$B$14 -> 0 | H7: =H6*'01 Inputs'!$B$14 -> 0 | I7: =I6*'01 Inputs'!$B$14 -> 0 | J7: =J6*'01 Inputs'!$B$14 -> 0 | ... AB7: =AB6*'01 Inputs'!$B$14 -> 0
B8: Equity contribution | C8: =C6*'01 Inputs'!$B$15 -> 13125000 | D8: =D6*'01 Inputs'!$B$15 -> 0 | E8: =E6*'01 Inputs'!$B$15 -> 0 | F8: =F6*'01 Inputs'!$B$15 -> 0 | G8: =G6*'01 Inputs'!$B$15 -> 0 | H8: =H6*'01 Inputs'!$B$15 -> 0 | I8: =I6*'01 Inputs'!$B$15 -> 0 | J8: =J6*'01 Inputs'!$B$15 -> 0 | ... AB8: =AB6*'01 Inputs'!$B$15 -> 0
B9: Funding Check | C9: =C6-C7-C8 -> 0 | D9: =D6-D7-D8 -> 0 | E9: =E6-E7-E8 -> 0 | F9: =F6-F7-F8 -> 0 | G9: =G6-G7-G8 -> 0 | H9: =H6-H7-H8 -> 0 | I9: =I6-I7-I8 -> 0 | J9: =J6-J7-J8 -> 0 | ... AB9: =AB6-AB7-AB8 -> 0

Sheet 04 Operation
B2: Operations
B4: Year | C4: ='02 Timeline'!C4 -> 0 | D4: ='02 Timeline'!D4 -> 1 | E4: ='02 Timeline'!E4 -> 2 | F4: ='02 Timeline'!F4 -> 3 | G4: ='02 Timeline'!G4 -> 4 | H4: ='02 Timeline'!H4 -> 5 | I4: ='02 Timeline'!I4 -> 6 | J4: ='02 Timeline'!J4 -> 7 | ... AB4: ='02 Timeline'!AB4 -> 25
B5: Operations flag | C5: ='02 Timeline'!C6 -> 0 | D5: ='02 Timeline'!D6 -> 1 | E5: ='02 Timeline'!E6 -> 1 | F5: ='02 Timeline'!F6 -> 1 | G5: ='02 Timeline'!G6 -> 1 | H5: ='02 Timeline'!H6 -> 1 | I5: ='02 Timeline'!I6 -> 1 | J5: ='02 Timeline'!J6 -> 1 | ... AB5: ='02 Timeline'!AB6 -> 1
B6: Capacity MW | C6: ='01 Inputs'!$B$6*C5 -> 0 | D6: ='01 Inputs'!$B$6*D5 -> 50 | E6: ='01 Inputs'!$B$6*E5 -> 50 | F6: ='01 Inputs'!$B$6*F5 -> 50 | G6: ='01 Inputs'!$B$6*G5 -> 50 | H6: ='01 Inputs'!$B$6*H5 -> 50 | I6: ='01 Inputs'!$B$6*I5 -> 50 | J6: ='01 Inputs'!$B$6*J5 -> 50 | ... AB6: ='01 Inputs'!$B$6*AB5 -> 50
B7: Capacity factor | C7: ='01 Inputs'!$B$8 -> 0.17 | D7: ='01 Inputs'!$B$8 -> 0.17 | E7: ='01 Inputs'!$B$8 -> 0.17 | F7: ='01 Inputs'!$B$8 -> 0.17 | G7: ='01 Inputs'!$B$8 -> 0.17 | H7: ='01 Inputs'!$B$8 -> 0.17 | I7: ='01 Inputs'!$B$8 -> 0.17 | J7: ='01 Inputs'!$B$8 -> 0.17 | ... AB7: ='01 Inputs'!$B$8 -> 0.17
B8: Gross generation MWh | C8: =C6*8760*C7 -> 0 | D8: =D6*8760*D7 -> 74460 | E8: =E6*8760*E7 -> 74460 | F8: =F6*8760*F7 -> 74460 | G8: =G6*8760*G7 -> 74460 | H8: =H6*8760*H7 -> 74460 | I8: =I6*8760*I7 -> 74460 | J8: =J6*8760*J7 -> 74460 | ... AB8: =AB6*8760*AB7 -> 74460
B9: Degradation factor | C9: =IF(C5=0,0,(1-'01 Inputs'!$B$9)^(C4-1)) -> 0 | D9: =IF(D5=0,0,(1-'01 Inputs'!$B$9)^(D4-1)) -> 1 | E9: =IF(E5=0,0,(1-'01 Inputs'!$B$9)^(E4-1)) -> 0.995 | F9: =IF(F5=0,0,(1-'01 Inputs'!$B$9)^(F4-1)) -> 0.990025 | G9: =IF(G5=0,0,(1-'01 Inputs'!$B$9)^(G4-1)) -> 0.98507488 | H9: =IF(H5=0,0,(1-'01 Inputs'!$B$9)^(H4-1)) -> 0.9801495 | I9: =IF(I5=0,0,(1-'01 Inputs'!$B$9)^(I4-1)) -> 0.97524875 | J9: =IF(J5=0,0,(1-'01 Inputs'!$B$9)^(J4-1)) -> 0.97037251 | ... AB9: =IF(AB5=0,0,(1-'01 Inputs'!$B$9)^(AB4-1)) -> 0.88665351
B10: Net generation MWh | C10: =C8*C9 -> 0 | D10: =D8*D9 -> 74460 | E10: =E8*E9 -> 74087.7 | F10: =F8*F9 -> 73717.262 | G10: =G8*G9 -> 73348.675 | H10: =H8*H9 -> 72981.932 | I10: =I8*I9 -> 72617.022 | J10: =J8*J9 -> 72253.937 | ... AB10: =AB8*AB9 -> 66020.22
B11: PPA price | C11: =IF(C5=0,0,'01 Inputs'!$B$10*(1+'01 Inputs'!$B$11)^(C4-1)) -> 0 | D11: =IF(D5=0,0,'01 Inputs'!$B$10*(1+'01 Inputs'!$B$11)^(D4-1)) -> 65 | E11: =IF(E5=0,0,'01 Inputs'!$B$10*(1+'01 Inputs'!$B$11)^(E4-1)) -> 66.3 | F11: =IF(F5=0,0,'01 Inputs'!$B$10*(1+'01 Inputs'!$B$11)^(F4-1)) -> 67.626 | G11: =IF(G5=0,0,'01 Inputs'!$B$10*(1+'01 Inputs'!$B$11)^(G4-1)) -> 68.97852 | H11: =IF(H5=0,0,'01 Inputs'!$B$10*(1+'01 Inputs'!$B$11)^(H4-1)) -> 70.35809 | I11: =IF(I5=0,0,'01 Inputs'!$B$10*(1+'01 Inputs'!$B$11)^(I4-1)) -> 71.765252 | J11: =IF(J5=0,0,'01 Inputs'!$B$10*(1+'01 Inputs'!$B$11)^(J4-1)) -> 73.200557 | ... AB11: =IF(AB5=0,0,'01 Inputs'!$B$10*(1+'01 Inputs'!$B$11)^(AB4-1)) -> 104.54842
B12: Revenue | C12: =C10*C11 -> 0 | D12: =D10*D11 -> 4839900 | E12: =E10*E11 -> 4912014.5 | F12: =F10*F11 -> 4985203.5 | G12: =G10*G11 -> 5059483.1 | H12: =H10*H11 -> 5134869.4 | I12: =I10*I11 -> 5211378.9 | J12: =J10*J11 -> 5289028.5 | ... AB12: =AB10*AB11 -> 6902309.8
B13: Opex | C13: =IF(C5=1,'01 Inputs'!$B$6*'01 Inputs'!$B$12*(1+'01 Inputs'!$B$13)^(C4-'01 Inputs'!$B$5),0) -> 0 | D13: =IF(D5=1,'01 Inputs'!$B$6*'01 Inputs'!$B$12*(1+'01 Inputs'!$B$13)^(D4-'01 Inputs'!$B$5),0) -> 750000 | E13: =IF(E5=1,'01 Inputs'!$B$6*'01 Inputs'!$B$12*(1+'01 Inputs'!$B$13)^(E4-'01 Inputs'!$B$5),0) -> 765000 | F13: =IF(F5=1,'01 Inputs'!$B$6*'01 Inputs'!$B$12*(1+'01 Inputs'!$B$13)^(F4-'01 Inputs'!$B$5),0) -> 780300 | G13: =IF(G5=1,'01 Inputs'!$B$6*'01 Inputs'!$B$12*(1+'01 Inputs'!$B$13)^(G4-'01 Inputs'!$B$5),0) -> 795906 | H13: =IF(H5=1,'01 Inputs'!$B$6*'01 Inputs'!$B$12*(1+'01 Inputs'!$B$13)^(H4-'01 Inputs'!$B$5),0) -> 811824.12 | I13: =IF(I5=1,'01 Inputs'!$B$6*'01 Inputs'!$B$12*(1+'01 Inputs'!$B$13)^(I4-'01 Inputs'!$B$5),0) -> 828060.6 | J13: =IF(J5=1,'01 Inputs'!$B$6*'01 Inputs'!$B$12*(1+'01 Inputs'!$B$13)^(J4-'01 Inputs'!$B$5),0) -> 844621.81 | ... AB13: =IF(AB5=1,'01 Inputs'!$B$6*'01 Inputs'!$B$12*(1+'01 Inputs'!$B$13)^(AB4-'01 Inputs'!$B$5),0) -> 1206327.9
B14: EBITDA | C14: =C12-C13 -> 0 | D14: =D12-D13 -> 4089900 | E14: =E12-E13 -> 4147014.5 | F14: =F12-F13 -> 4204903.5 | G14: =G12-G13 -> 4263577.1 | H14: =H12-H13 -> 4323045.2 | I14: =I12-I13 -> 4383318.3 | J14: =J12-J13 -> 4444406.6 | ... AB14: =AB12-AB13 -> 5695981.9

Sheet 05 Debt
B2: Debt Schedule
B4: Year | C4: ='02 Timeline'!C4 -> 0 | D4: ='02 Timeline'!D4 -> 1 | E4: ='02 Timeline'!E4 -> 2 | F4: ='02 Timeline'!F4 -> 3 | G4: ='02 Timeline'!G4 -> 4 | H4: ='02 Timeline'!H4 -> 5 | I4: ='02 Timeline'!I4 -> 6 | J4: ='02 Timeline'!J4 -> 7 | ... AB4: ='02 Timeline'!AB4 -> 25
B5: Opening debt | C5: =0 -> 0 | D5: =C10 -> 24375000 | E5: =D10 -> 22750000 | F5: =E10 -> 21125000 | G5: =F10 -> 19500000 | H5: =G10 -> 17875000 | I5: =H10 -> 16250000 | J5: =I10 -> 14625000 | K5: =J10 -> 13000000 | ... AB5: =AA10 -> 0
B6: Debt drawdown | C6: ='03 Construction'!C7 -> 24375000 | D6: ='03 Construction'!D7 -> 0 | E6: ='03 Construction'!E7 -> 0 | F6: ='03 Construction'!F7 -> 0 | G6: ='03 Construction'!G7 -> 0 | H6: ='03 Construction'!H7 -> 0 | I6: ='03 Construction'!I7 -> 0 | J6: ='03 Construction'!J7 -> 0 | ... AB6: ='03 Construction'!AB7 -> 0
B7: Interest | C7: =AVERAGE(C5,C10)*'01 Inputs'!$B$16 -> 792187.5 | D7: =AVERAGE(D5,D10)*'01 Inputs'!$B$16 -> 1531562.5 | E7: =AVERAGE(E5,E10)*'01 Inputs'!$B$16 -> 1425937.5 | F7: =AVERAGE(F5,F10)*'01 Inputs'!$B$16 -> 1320312.5 | G7: =AVERAGE(G5,G10)*'01 Inputs'!$B$16 -> 1214687.5 | H7: =AVERAGE(H5,H10)*'01 Inputs'!$B$16 -> 1109062.5 | I7: =AVERAGE(I5,I10)*'01 Inputs'!$B$16 -> 1003437.5 | J7: =AVERAGE(J5,J10)*'01 Inputs'!$B$16 -> 897812.5 | ... AB7: =AVERAGE(AB5,AB10)*'01 Inputs'!$B$16 -> 0
B8: Principal repayment | C8: =IF('02 Timeline'!C7=1,MIN(C5+C6,$C$12/'01 Inputs'!$B$17),0) -> 0 | D8: =IF('02 Timeline'!D7=1,MIN(D5+D6,$C$12/'01 Inputs'!$B$17),0) -> 1625000 | E8: =IF('02 Timeline'!E7=1,MIN(E5+E6,$C$12/'01 Inputs'!$B$17),0) -> 1625000 | F8: =IF('02 Timeline'!F7=1,MIN(F5+F6,$C$12/'01 Inputs'!$B$17),0) -> 1625000 | G8: =IF('02 Timeline'!G7=1,MIN(G5+G6,$C$12/'01 Inputs'!$B$17),0) -> 1625000 | H8: =IF('02 Timeline'!H7=1,MIN(H5+H6,$C$12/'01 Inputs'!$B$17),0) -> 1625000 | I8: =IF('02 Timeline'!I7=1,MIN(I5+I6,$C$12/'01 Inputs'!$B$17),0) -> 1625000 | J8: =IF('02 Timeline'!J7=1,MIN(J5+J6,$C$12/'01 Inputs'!$B$17),0) -> 1625000 | ... AB8: =IF('02 Timeline'!AB7=1,MIN(AB5+AB6,$C$12/'01 Inputs'!$B$17),0) -> 0
B9: Debt service | C9: =C7+C8 -> 792187.5 | D9: =D7+D8 -> 3156562.5 | E9: =E7+E8 -> 3050937.5 | F9: =F7+F8 -> 2945312.5 | G9: =G7+G8 -> 2839687.5 | H9: =H7+H8 -> 2734062.5 | I9: =I7+I8 -> 2628437.5 | J9: =J7+J8 -> 2522812.5 | ... AB9: =AB7+AB8 -> 0
B10: Closing debt | C10: =C5+C6-C8 -> 24375000 | D10: =D5+D6-D8 -> 22750000 | E10: =E5+E6-E8 -> 21125000 | F10: =F5+F6-F8 -> 19500000 | G10: =G5+G6-G8 -> 17875000 | H10: =H5+H6-H8 -> 16250000 | I10: =I5+I6-I8 -> 14625000 | J10: =J5+J6-J8 -> 13000000 | ... AB10: =AB5+AB6-AB8 -> 0
B12: Total debt | C12: =SUM(C6:AB6) -> 24375000 | D12: =SUM(D6:AC6) -> 0 | E12: =SUM(E6:AD6) -> 0 | F12: =SUM(F6:AE6) -> 0 | G12: =SUM(G6:AF6) -> 0 | H12: =SUM(H6:AG6) -> 0 | I12: =SUM(I6:AH6) -> 0 | J12: =SUM(J6:AI6) -> 0 | ... AB12: =SUM(AB6:BA6) -> 0

Sheet 06 Tax
B2: Tax
B4: Year | C4: ='02 Timeline'!C4 -> 0 | D4: ='02 Timeline'!D4 -> 1 | E4: ='02 Timeline'!E4 -> 2 | F4: ='02 Timeline'!F4 -> 3 | G4: ='02 Timeline'!G4 -> 4 | H4: ='02 Timeline'!H4 -> 5 | I4: ='02 Timeline'!I4 -> 6 | J4: ='02 Timeline'!J4 -> 7 | ... AB4: ='02 Timeline'!AB4 -> 25
B5: EBITDA | C5: ='04 Operation'!C14 -> 0 | D5: ='04 Operation'!D14 -> 4089900 | E5: ='04 Operation'!E14 -> 4147014.5 | F5: ='04 Operation'!F14 -> 4204903.5 | G5: ='04 Operation'!G14 -> 4263577.1 | H5: ='04 Operation'!H14 -> 4323045.2 | I5: ='04 Operation'!I14 -> 4383318.3 | J5: ='04 Operation'!J14 -> 4444406.6 | ... AB5: ='04 Operation'!AB14 -> 5695981.9
B6: Interest | C6: ='05 Debt'!C7 -> 792187.5 | D6: ='05 Debt'!D7 -> 1531562.5 | E6: ='05 Debt'!E7 -> 1425937.5 | F6: ='05 Debt'!F7 -> 1320312.5 | G6: ='05 Debt'!G7 -> 1214687.5 | H6: ='05 Debt'!H7 -> 1109062.5 | I6: ='05 Debt'!I7 -> 1003437.5 | J6: ='05 Debt'!J7 -> 897812.5 | ... AB6: ='05 Debt'!AB7 -> 0
B7: Taxable income | C7: =MAX(C5-C6,0) -> 0 | D7: =MAX(D5-D6,0) -> 2558337.5 | E7: =MAX(E5-E6,0) -> 2721077 | F7: =MAX(F5-F6,0) -> 2884591 | G7: =MAX(G5-G6,0) -> 3048889.6 | H7: =MAX(H5-H6,0) -> 3213982.7 | I7: =MAX(I5-I6,0) -> 3379880.8 | J7: =MAX(J5-J6,0) -> 3546594.1 | ... AB7: =MAX(AB5-AB6,0) -> 5695981.9
B8: Tax | C8: =C7*'01 Inputs'!$B$18 -> 0 | D8: =D7*'01 Inputs'!$B$18 -> 639584.38 | E8: =E7*'01 Inputs'!$B$18 -> 680269.25 | F8: =F7*'01 Inputs'!$B$18 -> 721147.76 | G8: =G7*'01 Inputs'!$B$18 -> 762222.39 | H8: =H7*'01 Inputs'!$B$18 -> 803495.68 | I8: =I7*'01 Inputs'!$B$18 -> 844970.2 | J8: =J7*'01 Inputs'!$B$18 -> 886648.54 | ... AB8: =AB7*'01 Inputs'!$B$18 -> 1423995.5

Sheet 07 Cash Flow
B2: Cash Flow
B4: Year | C4: ='02 Timeline'!C4 -> 0 | D4: ='02 Timeline'!D4 -> 1 | E4: ='02 Timeline'!E4 -> 2 | F4: ='02 Timeline'!F4 -> 3 | G4: ='02 Timeline'!G4 -> 4 | H4: ='02 Timeline'!H4 -> 5 | I4: ='02 Timeline'!I4 -> 6 | J4: ='02 Timeline'!J4 -> 7 | ... AB4: ='02 Timeline'!AB4 -> 25
B5: EBITDA | C5: ='04 Operation'!C14 -> 0 | D5: ='04 Operation'!D14 -> 4089900 | E5: ='04 Operation'!E14 -> 4147014.5 | F5: ='04 Operation'!F14 -> 4204903.5 | G5: ='04 Operation'!G14 -> 4263577.1 | H5: ='04 Operation'!H14 -> 4323045.2 | I5: ='04 Operation'!I14 -> 4383318.3 | J5: ='04 Operation'!J14 -> 4444406.6 | ... AB5: ='04 Operation'!AB14 -> 5695981.9
B6: Tax | C6: ='06 Tax'!C8 -> 0 | D6: ='06 Tax'!D8 -> 639584.38 | E6: ='06 Tax'!E8 -> 680269.25 | F6: ='06 Tax'!F8 -> 721147.76 | G6: ='06 Tax'!G8 -> 762222.39 | H6: ='06 Tax'!H8 -> 803495.68 | I6: ='06 Tax'!I8 -> 844970.2 | J6: ='06 Tax'!J8 -> 886648.54 | ... AB6: ='06 Tax'!AB8 -> 1423995.5
B7: CFADS | C7: =C5-C6 -> 0 | D7: =D5-D6 -> 3450315.6 | E7: =E5-E6 -> 3466745.3 | F7: =F5-F6 -> 3483755.8 | G7: =G5-G6 -> 3501354.7 | H7: =H5-H6 -> 3519549.6 | I7: =I5-I6 -> 3538348.1 | J7: =J5-J6 -> 3557758.1 | ... AB7: =AB5-AB6 -> 4271986.4
B8: Interest | C8: ='05 Debt'!C7 -> 792187.5 | D8: ='05 Debt'!D7 -> 1531562.5 | E8: ='05 Debt'!E7 -> 1425937.5 | F8: ='05 Debt'!F7 -> 1320312.5 | G8: ='05 Debt'!G7 -> 1214687.5 | H8: ='05 Debt'!H7 -> 1109062.5 | I8: ='05 Debt'!I7 -> 1003437.5 | J8: ='05 Debt'!J7 -> 897812.5 | ... AB8: ='05 Debt'!AB7 -> 0
B9: Principal | C9: ='05 Debt'!C8 -> 0 | D9: ='05 Debt'!D8 -> 1625000 | E9: ='05 Debt'!E8 -> 1625000 | F9: ='05 Debt'!F8 -> 1625000 | G9: ='05 Debt'!G8 -> 1625000 | H9: ='05 Debt'!H8 -> 1625000 | I9: ='05 Debt'!I8 -> 1625000 | J9: ='05 Debt'!J8 -> 1625000 | ... AB9: ='05 Debt'!AB8 -> 0
B10: Debt service | C10: =C8+C9 -> 792187.5 | D10: =D8+D9 -> 3156562.5 | E10: =E8+E9 -> 3050937.5 | F10: =F8+F9 -> 2945312.5 | G10: =G8+G9 -> 2839687.5 | H10: =H8+H9 -> 2734062.5 | I10: =I8+I9 -> 2628437.5 | J10: =J8+J9 -> 2522812.5 | ... AB10: =AB8+AB9 -> 0
B11: Cash after debt | C11: =C7-C10 -> -792187.5 | D11: =D7-D10 -> 293753.12 | E11: =E7-E10 -> 415807.76 | F11: =F7-F10 -> 538443.27 | G11: =G7-G10 -> 661667.17 | H11: =H7-H10 -> 785487.05 | I11: =I7-I10 -> 909910.61 | J11: =J7-J10 -> 1034945.6 | ... AB11: =AB7-AB10 -> 4271986.4
B12: Equity Construction | C12: =-'03 Construction'!C8 -> -13125000 | D12: =-'03 Construction'!D8 -> 0 | E12: =-'03 Construction'!E8 -> 0 | F12: =-'03 Construction'!F8 -> 0 | G12: =-'03 Construction'!G8 -> 0 | H12: =-'03 Construction'!H8 -> 0 | I12: =-'03 Construction'!I8 -> 0 | J12: =-'03 Construction'!J8 -> 0 | ... AB12: =-'03 Construction'!AB8 -> 0
B13: Equity cash flow | C13: =C11+C12 -> -13917188 | D13: =D11+D12 -> 293753.12 | E13: =E11+E12 -> 415807.76 | F13: =F11+F12 -> 538443.27 | G13: =G11+G12 -> 661667.17 | H13: =H11+H12 -> 785487.05 | I13: =I11+I12 -> 909910.61 | J13: =J11+J12 -> 1034945.6 | ... AB13: =AB11+AB12 -> 4271986.4

Sheet 08 Returns
B2: Returns
B4: Year | C4: ='02 Timeline'!C4 -> 0 | D4: ='02 Timeline'!D4 -> 1 | E4: ='02 Timeline'!E4 -> 2 | F4: ='02 Timeline'!F4 -> 3 | G4: ='02 Timeline'!G4 -> 4 | H4: ='02 Timeline'!H4 -> 5 | I4: ='02 Timeline'!I4 -> 6 | J4: ='02 Timeline'!J4 -> 7 | ... AB4: ='02 Timeline'!AB4 -> 25
B5: CFADS | C5: ='07 Cash Flow'!C7 -> 0 | D5: ='07 Cash Flow'!D7 -> 3450315.6 | E5: ='07 Cash Flow'!E7 -> 3466745.3 | F5: ='07 Cash Flow'!F7 -> 3483755.8 | G5: ='07 Cash Flow'!G7 -> 3501354.7 | H5: ='07 Cash Flow'!H7 -> 3519549.6 | I5: ='07 Cash Flow'!I7 -> 3538348.1 | J5: ='07 Cash Flow'!J7 -> 3557758.1 | ... AB5: ='07 Cash Flow'!AB7 -> 4271986.4
B6: Debt service | C6: ='07 Cash Flow'!C10 -> 792187.5 | D6: ='07 Cash Flow'!D10 -> 3156562.5 | E6: ='07 Cash Flow'!E10 -> 3050937.5 | F6: ='07 Cash Flow'!F10 -> 2945312.5 | G6: ='07 Cash Flow'!G10 -> 2839687.5 | H6: ='07 Cash Flow'!H10 -> 2734062.5 | I6: ='07 Cash Flow'!I10 -> 2628437.5 | J6: ='07 Cash Flow'!J10 -> 2522812.5 | ... AB6: ='07 Cash Flow'!AB10 -> 0
B7: DSCR | C7: =IF(C6>0,C5/C6,"") -> 0 | D7: =IF(D6>0,D5/D6,"") -> 1.0930611 | E7: =IF(E6>0,E5/E6,"") -> 1.1362885 | F7: =IF(F6>0,F5/F6,"") -> 1.1828136 | G7: =IF(G6>0,G5/G6,"") -> 1.233007 | H7: =IF(H6>0,H5/H6,"") -> 1.2872967 | I7: =IF(I6>0,I5/I6,"") -> 1.3461793 | J7: =IF(J6>0,J5/J6,"") -> 1.4102348 | ... AB7: =IF(AB6>0,AB5/AB6,"")
B8: Closing debt | C8: ='05 Debt'!C10 -> 24375000 | D8: ='05 Debt'!D10 -> 22750000 | E8: ='05 Debt'!E10 -> 21125000 | F8: ='05 Debt'!F10 -> 19500000 | G8: ='05 Debt'!G10 -> 17875000 | H8: ='05 Debt'!H10 -> 16250000 | I8: ='05 Debt'!I10 -> 14625000 | J8: ='05 Debt'!J10 -> 13000000 | ... AB8: ='05 Debt'!AB10 -> 0
B9: Equity cash flow | C9: ='07 Cash Flow'!C13 -> -13917188 | D9: ='07 Cash Flow'!D13 -> 293753.12 | E9: ='07 Cash Flow'!E13 -> 415807.76 | F9: ='07 Cash Flow'!F13 -> 538443.27 | G9: ='07 Cash Flow'!G13 -> 661667.17 | H9: ='07 Cash Flow'!H13 -> 785487.05 | I9: ='07 Cash Flow'!I13 -> 909910.61 | J9: ='07 Cash Flow'!J13 -> 1034945.6 | ... AB9: ='07 Cash Flow'!AB13 -> 4271986.4
B10: Project cash flow | C10: ='04 Operation'!C14-'06 Tax'!C8-'03 Construction'!C6 -> -37500000 | D10: ='04 Operation'!D14-'06 Tax'!D8-'03 Construction'!D6 -> 3450315.6 | E10: ='04 Operation'!E14-'06 Tax'!E8-'03 Construction'!E6 -> 3466745.3 | F10: ='04 Operation'!F14-'06 Tax'!F8-'03 Construction'!F6 -> 3483755.8 | G10: ='04 Operation'!G14-'06 Tax'!G8-'03 Construction'!G6 -> 3501354.7 | H10: ='04 Operation'!H14-'06 Tax'!H8-'03 Construction'!H6 -> 3519549.6 | I10: ='04 Operation'!I14-'06 Tax'!I8-'03 Construction'!I6 -> 3538348.1 | J10: ='04 Operation'!J14-'06 Tax'!J8-'03 Construction'!J6 -> 3557758.1 | ... AB10: ='04 Operation'!AB14-'06 Tax'!AB8-'03 Construction'!AB6 -> 4271986.4
B12: Minimum DCSR | C12: =MIN(D7:R7) -> 1.0930611
B13: Average DCSR | C13: =AVERAGE(D7:R7) -> 1.5464882
B14: Equity IRR | C14: =IRR(C9:AB9) -> 0.094986304
B15: Project IRR
B16: LLCR

Sheet 09 Sensitivities
B2: Scenario Analysis
B4: Scenario | C4: Capex change | D4: PPA price change | E4: Generation change | F4: Interest change | G4: Equity IRR | H4: Min DSCR
B5: Downside | C5: 0.1 | D5: -0.1 | E5: -0.05 | F5: 0.01
B6: Basse | C6: 0 | D6: 0 | E6: 0 | F6: 0
B7: Upside | C7: -5 | D7: 10 | E7: 5 | F7: -0.5

Sheet 10 Dashboard

Sheet 11 Checks
B2: Model Checks
C3: Value | D3: Status
B4: Funding check | C4: =SUM('03 Construction'!C9:AB9) -> 0 | D4: =IF(ABS(C4)<1,"OK","Error") -> OK
B5: Final debt check | C5: ='05 Debt'!AB10 -> 0 | D5: =IF(ABS(C5)<1,"OK","Error") -> OK
B6: Minimum DSCR | C6: ='08 Returns'!C12 -> 1.0930611 | D6: =IF(C6>1.2,"OK","Weak") -> Weak
B7: Equity IRR | C7: ='08 Returns'!C14 -> 0.094986304 | D7: =IF(C7>0,"OK","Error") -> OK
